{
    "71": 10,
    "26": 9,
    "92": 8,
    "241": 7,
    "28": 6,
    "123": 5,
    "61": 4,
    "162": 3,
    "139": 2,
    "135": 1,
    "111": 50,
    "14": 48,
    "160": 47,
    "118": 46,
    "35": 45,
    "93": 44,
    "49": 42,
    "272": 40,
    "113": 39,
    "206": 38,
    "13": 37,
    "291": 36,
    "161": 35,
    "253": 34,
    "163": 33,
    "12": 32,
    "141": 31,
    "273": 30,
    "2": 29,
    "182": 28,
    "245": 27,
    "283": 26,
    "22": 25,
    "271": 24,
    "173": 23,
    "292": 22,
    "74": 21,
    "122": 20,
    "183": 19,
    "286": 18,
    "232": 17,
    "223": 16,
    "233": 15,
    "225": 14,
    "152": 13,
    "153": 12,
    "11": 11,
    "21": 100,
    "268": 97,
    "54": 94,
    "172": 93,
    "200": 92,
    "224": 91,
    "130": 90,
    "284": 89,
    "82": 88,
    "251": 87,
    "164": 86,
    "7": 85,
    "4": 84,
    "261": 83,
    "262": 82,
    "103": 81,
    "64": 80,
    "80": 78,
    "133": 77,
    "134": 76,
    "151": 75,
    "116": 74,
    "282": 73,
    "287": 71,
    "185": 70,
    "178": 69,
    "275": 68,
    "181": 67,
    "129": 66,
    "6": 62,
    "242": 60,
    "155": 59,
    "157": 58,
    "221": 57,
    "42": 56,
    "102": 55,
    "184": 54,
    "249": 53,
    "234": 52
}